[{"company_name": "Chic Antique", "invoice_reference": {"number": "47561", "date": "14-08-2024"}, "articles": [{"reference": "25069913", "designation": "Lanterne, H46,5/L32/L32 cm antique laiton", "quantity": 2, "unit_price": 58, "total_price": 116}, {"reference": "61033102", "designation": "Linas Couverts avec d\u00e9cor argent set 4, L23 cm antique nacre", "quantity": 16, "unit_price": 4.6, "total_price": 73.6}, {"reference": "61049627", "designation": "Nordique Couvert set de 4, L23 cm or", "quantity": 6, "unit_price": 11, "total_price": 66}, {"reference": "39091419", "designation": "Bol Forme de coquillage, H6,5/D16,5 cm cr\u00e8me", "quantity": 6, "unit_price": 9, "total_price": 54}, {"reference": "61049327", "designation": "Nordique cuill\u00e8re caf\u00e9 au lait, L19,5 cm or", "quantity": 36, "unit_price": 2, "total_price": 72}, {"reference": "40041113", "designation": "\u00c9tag\u00e8re avec 3 \u00e9tag\u00e8res, H186,5/L167/L38 cm antique laiton", "quantity": 1, "unit_price": 515, "total_price": 515}, {"reference": "40047500", "designation": "Grimaud Table de Service, H76/L122/L26 cm nature", "quantity": 1, "unit_price": 178, "total_price": 178}, {"reference": "1616", "designation": "Emballages et contributions environnementales", "quantity": 1, "unit_price": 13, "total_price": 13}]}, {"company_name": "by Room", "invoice_reference": {"number": "37661", "date": "17. September 2024"}, "articles": [{"reference": "17881", "designation": "2 Colored candleholder Olive green / Dusty Pink", "quantity": 6, "unit_price": 4.9, "total_price": 29.4}, {"reference": "17867", "designation": "2 colored candleholder Dusty green/ Blue", "quantity": 6, "unit_price": 4.9, "total_price": 29.4}, {"reference": "17862", "designation": "Large Candleholder Champagne 23 x 12 cm", "quantity": 6, "unit_price": 6, "total_price": 36}, {"reference": "17420", "designation": "Candle holder multicolor,pink/", "quantity": 6, "unit_price": 9.9, "total_price": 59.4}, {"reference": "16742", "designation": "Vase Large Turquise 18x8", "quantity": 6, "unit_price": 4.5, "total_price": 27}, {"reference": "16728", "designation": "Vase Small petrol blue 11x8", "quantity": 6, "unit_price": 3.9, "total_price": 23.4}, {"reference": "17865", "designation": "Candleholder Granny Plum 19 x 10 cm", "quantity": 6, "unit_price": 5.3, "total_price": 31.8}, {"reference": "17870", "designation": "Candleholder Multi Lightblue/Champagne 25 x 10 cm", "quantity": 6, "unit_price": 9.9, "total_price": 59.4}, {"reference": "18160", "designation": "Cushion rusty red w/print 50x50, incl. filler", "quantity": 2, "unit_price": 15.9, "total_price": 31.8}, {"reference": "18157", "designation": "Cushion Olive green w/print 50x50, incl. filler", "quantity": 2, "unit_price": 15.9, "total_price": 31.8}, {"reference": "17777", "designation": "Bottle openers Sea, set of 4", "quantity": 2, "unit_price": 25.9, "total_price": 51.8}, {"reference": "15815", "designation": "Glass Bowl clear, Acorn 11x8cm", "quantity": 6, "unit_price": 3.75, "total_price": 22.5}, {"reference": "18732", "designation": "Vase large w/ears green, ceramic", "quantity": 0, "unit_price": 22, "total_price": 0}, {"reference": "18775", "designation": "Bar set, set of 3, aqua, stainless steel, handmade", "quantity": 0, "unit_price": 9.95, "total_price": 0}, {"reference": "18633-38", "designation": "Bowl 38cm, olive green pearl handpainted, mango wood", "quantity": 0, "unit_price": 36.9, "total_price": 0}, {"reference": "18633-23", "designation": "Bowl 25cm, olive green pearl handpainted, mango wood", "quantity": 0, "unit_price": 21.9, "total_price": 0}, {"reference": "18633-18", "designation": "Bowl 18cm, olive green pearl handpainted, mango wood", "quantity": 0, "unit_price": 13.25, "total_price": 0}, {"reference": "18633-SS", "designation": "Salad servers, olive pearl, mango wood", "quantity": 0, "unit_price": 7.9, "total_price": 0}, {"reference": "17537", "designation": "Chopping board S/2 Flower", "quantity": 2, "unit_price": 26.9, "total_price": 53.8}, {"reference": "15793", "designation": "Candle holder Dusty Green 17x11 cm", "quantity": 6, "unit_price": 4.9, "total_price": 29.4}, {"reference": "14853", "designation": "Candlestand Small Smoke10x9", "quantity": 6, "unit_price": 3.9, "total_price": 23.4}, {"reference": "15791", "designation": "Candleholder Granny 19x10cm Turquise", "quantity": 6, "unit_price": 5.3, "total_price": 31.8}, {"reference": "16744", "designation": "Candle holder Turquise Harlequin 10 x 11 cm", "quantity": 6, "unit_price": 3.5, "total_price": 21}, {"reference": "17856", "designation": "Small Candleholder, Dusty Olive Harlequin", "quantity": 4, "unit_price": 3.9, "total_price": 15.6}, {"reference": "15393", "designation": "Salad servers, lemon bird, mango wood", "quantity": 0, "unit_price": 7.9, "total_price": 0}, {"reference": "18174", "designation": "Bowl 18cm, orange bird, mango wood", "quantity": 0, "unit_price": 13.25, "total_price": 0}, {"reference": "18175", "designation": "Bowl 25cm, orange bird, mango wood", "quantity": 0, "unit_price": 21.9, "total_price": 0}, {"reference": "18176", "designation": "Bowl 38cm, orange bird, mango wood", "quantity": 0, "unit_price": 36.9, "total_price": 0}, {"reference": "18177", "designation": "Salad servers, orange bird, mango wood", "quantity": 0, "unit_price": 7.9, "total_price": 0}, {"reference": "14288", "designation": "Bowl 18cm, lemon, mango wood", "quantity": 0, "unit_price": 13.25, "total_price": 0}, {"reference": "14289", "designation": "Bowl 25cm, lemon, mango wood", "quantity": 0, "unit_price": 21.9, "total_price": 0}, {"reference": "14290", "designation": "Bowl 38cm, lemon, mango wood", "quantity": 0, "unit_price": 36.9, "total_price": 0}, {"reference": "14291", "designation": "Salad servers, lemon, mango wood", "quantity": 0, "unit_price": 7.9, "total_price": 0}, {"reference": "17843", "designation": "Trays, set of 3, diff. colors, mango", "quantity": 1, "unit_price": 89, "total_price": 89}, {"reference": "18536", "designation": "Trays rectangle mango, set of 2, white w/ eucalyptus leaves", "quantity": 0, "unit_price": 21, "total_price": 0}, {"reference": "18535", "designation": "Trays round, set of 4, white w/eucalyptus leaves, mango wood", "quantity": 0, "unit_price": 45, "total_price": 0}, {"reference": "17855", "designation": "Small Candleholder, Amber 10 x 11 cm", "quantity": 6, "unit_price": 3.9, "total_price": 23.4}, {"reference": "14843", "designation": "Candlestand Yellow 16x9cm", "quantity": 0, "unit_price": 4, "total_price": 0}, {"reference": "17879", "designation": "Candleholder Granny Orange 19 x 10 cm", "quantity": 6, "unit_price": 5.3, "total_price": 31.8}, {"reference": "15787", "designation": "Candle holder Dusty Orange Harlequin 10x11 cm", "quantity": 6, "unit_price": 3.9, "total_price": 23.4}, {"reference": "14844", "designation": "Vase Small Yellow 11x8cm", "quantity": 6, "unit_price": 3.2, "total_price": 19.2}, {"reference": "17813", "designation": "Trays white pearl, set of 3, mango", "quantity": 1, "unit_price": 89, "total_price": 89}, {"reference": "17979", "designation": "Salad servers, red starfish, mango wood", "quantity": 2, "unit_price": 7.9, "total_price": 15.8}, {"reference": "18538", "designation": "Tray round mango, set of 4, White with lobster", "quantity": 2, "unit_price": 45, "total_price": 90}, {"reference": "18714", "designation": "Bowl, set of 2, white, 23x10/30x10, mango wood", "quantity": 2, "unit_price": 29.9, "total_price": 59.8}, {"reference": "18328", "designation": "Mango plate set of 2 white enamel", "quantity": 2, "unit_price": 26.9, "total_price": 53.8}, {"reference": "18729", "designation": "Vase small round, w/dots, green/blue, ceramic", "quantity": 0, "unit_price": 18, "total_price": 0}, {"reference": "18728", "designation": "Vase big round w/dots, blue/green, ceramic", "quantity": 0, "unit_price": 55, "total_price": 0}, {"reference": "18054", "designation": "Scarf blue/white print and silk borders, block print 120X160", "quantity": 3, "unit_price": 14.9, "total_price": 44.7}, {"reference": "18053", "designation": "Scarf green w/multiprint and silk borders, block print 120X160", "quantity": 3, "unit_price": 14.9, "total_price": 44.7}, {"reference": "18048", "designation": "Scarf blue W/flower and silk boarder, block print 120X160", "quantity": 0, "unit_price": 14.9, "total_price": 0}, {"reference": "18047", "designation": "Scarf red/black W/silk boarder, block print 120X160", "quantity": 3, "unit_price": 14.9, "total_price": 44.7}, {"reference": "18050", "designation": "Scarf grey W/flower and silk borders, block print 120X160", "quantity": 3, "unit_price": 14.9, "total_price": 44.7}, {"reference": "18052", "designation": "Scarf blue W/fishbone and silk boarder, block print 120X160", "quantity": 3, "unit_price": 14.9, "total_price": 44.7}, {"reference": "Fuel fee 3%", "designation": "Due to heavy price increases on fuel and oil.", "quantity": 1, "unit_price": 38, "total_price": 38}, {"reference": "Freight 60x80x140 70kg", "designation": "Freight 60x80x140 70kg", "quantity": 1, "unit_price": 95, "total_price": 95}]}]